urldl.py
urldl-1.1.2.dist-info/LICENSE
urldl-1.1.2.dist-info/METADATA
urldl-1.1.2.dist-info/WHEEL
urldl-1.1.2.dist-info/top_level.txt
urldl-1.1.2.dist-info/RECORD
