Metadata-Version: 2.1
Name: urldl
Version: 1.1.2
Summary: URL content downloader
Home-page: UNKNOWN
Author: Fayas Noushad
License: MIT
Project-URL: Tracker, https://github.com/FayasNoushad/URL-Download/issues
Project-URL: Source, https://github.com/FayasNoushad/URL-Download
Platform: UNKNOWN
Classifier: Intended Audience :: Developers
Classifier: Natural Language :: English
Classifier: Programming Language :: Python
Classifier: License :: OSI Approved :: MIT License
Classifier: Operating System :: OS Independent
Requires-Python: >=3.6
License-File: LICENSE
Requires-Dist: requests
Requires-Dist: domain-extract
